Week10/ex2/ex2.v
module ex2 
  (
   x,
   y,
   carry_in,
   z,
   carry_out
   );
	
  input  x;
  input  y;
  input  carry_in;
  output z;
  output carry_out;
  
  wire w1;
  wire w2;
  wire w3;
  
  assign w1 = x ^ y;
  assign w2 = w1 & carry_in;
  assign w3 = x & y;
  
  assign z   = w1 ^ carry_in;
  assign carry_out = w2 | w3;
  
endmodule

Week10/ex2/testbench.v
module testbench;

// input and output test signals
reg a, b, carry_in;

wire carry_out, sum;

// creating the instance of the module we want to test
ex2 fa(a, b, carry_in, sum, carry_out);

initial
begin
a = 1'b0;
b = 1'b1;
carry_in = 1'b0;
#5; // pause (5 units of delay )
carry_in = 1'b1;
#5;
a = 1'b1;
b = 1'b0;
#5;
carry_in = 1'b0;
#5
a = 1'b0;
b = 1'b0;
#5
carry_in = 1'b1;
#5
a = 1'b1;
b = 1'b1;
#5;
carry_in = 1'b0;
end

// print signal values on every change
initial
$monitor("a= %b b = %b carry_in = %b sum = %b carry_out = %b", a, b, carry_in, sum, carry_out);

initial
$dumpvars;

endmodule

Week10/ex2/simulation/modelsim/dump.vcd
$date
	Thu Nov 05 19:34:07 2020
$end
$version
	ModelSim Version 10.5b
$end
$timescale
	1ps
$end

$scope module testbench $end
$var reg 1 ! a $end
$var reg 1 " b $end
$var reg 1 # carry_in $end
$var wire 1 $ carry_out $end
$var wire 1 % sum $end

$scope module fa $end
$var wire 1 & x $end
$var wire 1 ' y $end
$var wire 1 ( carry_in $end
$var wire 1 % z $end
$var wire 1 $ carry_out $end
$var wire 1 ) w1 $end
$var wire 1 * w2 $end
$var wire 1 + w3 $end
$upscope $end
$upscope $end
$enddefinitions $end
#0
$dumpvars
0!
1"
0#
0$
1%
1)
0*
0+
0(
1'
0&
$end
#5
1#
1(
1*
0%
1$
#10
1!
0"
1&
0'
#15
0#
0(
0*
1%
0$
#20
0!
0&
0)
0%
#25
1#
1(
1%
#30
1!
1"
1&
1'
1+
1$
#35
0#
0(
0%
